chasing_targets_gym/run.py
chasing_targets_gym/_planner.pyi
chasing_targets_gym/py_planner.py
chasing_targets_gym/render.py
chasing_targets_gym/__init__.py
chasing_targets_gym/_planner.cpython-311-x86_64-linux-gnu.so
chasing_targets_gym/sim.py
chasing_targets_gym/robots.py
chasing_targets_gym-0.1.0.dist-info/METADATA
chasing_targets_gym-0.1.0.dist-info/RECORD
chasing_targets_gym-0.1.0.dist-info/WHEEL
chasing_targets_gym-0.1.0.dist-info/entry_points.txt
chasing_targets_gym-0.1.0.dist-info/licenses/LICENSE
