Metadata-Version: 2.1
Name: chasing_targets_gym
Version: 0.1.0
Summary: Simple gym environment for multiple agents to chase multiple (dumb) targets
Author-Email: Bryce Ferenczi <frenzi@hotmail.com.au>
License: MIT License
Classifier: Development Status :: 4 - Beta
Classifier: Intended Audience :: Developers
Classifier: Programming Language :: Python :: 3.10
Classifier: Programming Language :: Python :: 3.11
Classifier: Programming Language :: Python :: 3.12
Classifier: License :: OSI Approved :: MIT License
Classifier: Operating System :: OS Independent
Classifier: Natural Language :: English
Project-URL: Homepage, https://github.com/5had3z/chasing-targets-gym
Project-URL: Bug tracker, https://github.com/5had3z/chasing-targets-gym/issues
Requires-Python: >=3.10
Requires-Dist: numpy
Requires-Dist: gymnasium>=0.28.1
Requires-Dist: pygame
